README.md
setup.py
ivtest/EF.py
ivtest/__init__.py
ivtest/_version.py
ivtest/correlation_analysis.py
ivtest/macro_analysis.py
ivtest.egg-info/PKG-INFO
ivtest.egg-info/SOURCES.txt
ivtest.egg-info/dependency_links.txt
ivtest.egg-info/requires.txt
ivtest.egg-info/top_level.txt