Metadata-Version: 1.1
Name: ivtest
Version: 0.0.2
Summary: my test
Home-page: UNKNOWN
Author: ivey
Author-email: iveyzhang@outlook.com
License: MIT
Platform: UNKNOWN
Classifier: Development Status :: 4 - Beta
Classifier: Intended Audience :: Developers
Classifier: Topic :: System :: Logging
Classifier: License :: OSI Approved :: MIT License
Classifier: Programming Language :: Python :: 3
